fastapi_qengine/__init__.py
fastapi_qengine/dependency.py
fastapi_qengine/openapi_schema.py
fastapi_qengine/py.typed
fastapi_qengine/backends/__init__.py
fastapi_qengine/backends/beanie/__init__.py
fastapi_qengine/backends/beanie/adapter.py
fastapi_qengine/backends/beanie/compiler.py
fastapi_qengine/backends/beanie/engine.py
fastapi_qengine/backends/beanie/operators.py
fastapi_qengine/core/__init__.py
fastapi_qengine/core/ast.py
fastapi_qengine/core/compiler_base.py
fastapi_qengine/core/config.py
fastapi_qengine/core/errors.py
fastapi_qengine/core/normalizer.py
fastapi_qengine/core/optimizer.py
fastapi_qengine/core/parser.py
fastapi_qengine/core/registry.py
fastapi_qengine/core/response.py
fastapi_qengine/core/types.py
fastapi_qengine/core/validator.py
fastapi_qengine/operators/__init__.py
fastapi_qengine/operators/base/__init__.py
fastapi_qengine/operators/base/registry.py
fastapi_qengine-0.7.0.dist-info/METADATA
fastapi_qengine-0.7.0.dist-info/WHEEL
fastapi_qengine-0.7.0.dist-info/top_level.txt
fastapi_qengine-0.7.0.dist-info/RECORD
