Metadata-Version: 2.4
Name: fastapi-qengine
Version: 0.7.0
Summary: fastapi-qengine is an advanced query engine for FastAPI, inspired by Loopback 4's filtering system. It allows building complex queries directly from URLs with a flexible syntax.
Author-email: Uriel Curiel <kratoz.00616@gmail.com>
Project-URL: Repository, https://github.com/urielcuriel/fastapi-qengine
Keywords: fastapi,beanie,mongodb,query,filter,engine
Classifier: Framework :: FastAPI
Classifier: Programming Language :: Python :: 3.9
Classifier: Programming Language :: Python :: 3.10
Classifier: Programming Language :: Python :: 3.11
Classifier: Programming Language :: Python :: 3.12
Requires-Python: >=3.9
Provides-Extra: dev
Requires-Dist: fastapi; extra == "dev"
Requires-Dist: beanie; extra == "dev"
Requires-Dist: pydantic>=2.11.3; extra == "dev"
Requires-Dist: uvicorn[standard]; extra == "dev"
Requires-Dist: fastapi-pagination; extra == "dev"
Requires-Dist: pytest>=7.0.0; extra == "dev"
Requires-Dist: pytest-asyncio>=0.21.0; extra == "dev"
Requires-Dist: httpx; extra == "dev"
Requires-Dist: pymongo>=4.0.0; extra == "dev"
Requires-Dist: pyrefly; extra == "dev"
Requires-Dist: ruff; extra == "dev"
Requires-Dist: basedpyright>=1.31.7; extra == "dev"
Provides-Extra: test
Requires-Dist: pytest>=7.0.0; extra == "test"
Requires-Dist: pytest-asyncio>=0.21.0; extra == "test"
Requires-Dist: pytest-cov>=4.0.0; extra == "test"
Requires-Dist: httpx; extra == "test"
Provides-Extra: docs
Requires-Dist: pydoc-markdown>=4.8.2; extra == "docs"
Requires-Dist: pydoc-markdown-nuxt==0.2.1; extra == "docs"
